next_gen_ui_agent/__init__.py
next_gen_ui_agent/agent.py
next_gen_ui_agent/agent_config.py
next_gen_ui_agent/array_field_reducer.py
next_gen_ui_agent/component_selection_llm_onestep.py
next_gen_ui_agent/component_selection_llm_strategy.py
next_gen_ui_agent/component_selection_llm_twostep.py
next_gen_ui_agent/component_selection_pertype.py
next_gen_ui_agent/data_structure_tools.py
next_gen_ui_agent/data_transformation.py
next_gen_ui_agent/design_system_handler.py
next_gen_ui_agent/json_data_wrapper.py
next_gen_ui_agent/model.py
next_gen_ui_agent/spec_schema.py
next_gen_ui_agent/types.py
next_gen_ui_agent/data_transform/__init__.py
next_gen_ui_agent/data_transform/audio.py
next_gen_ui_agent/data_transform/data_transformer.py
next_gen_ui_agent/data_transform/data_transformer_utils.py
next_gen_ui_agent/data_transform/hand_build_component.py
next_gen_ui_agent/data_transform/image.py
next_gen_ui_agent/data_transform/json_schema_config.py
next_gen_ui_agent/data_transform/one_card.py
next_gen_ui_agent/data_transform/set_of_cards.py
next_gen_ui_agent/data_transform/table.py
next_gen_ui_agent/data_transform/types.py
next_gen_ui_agent/data_transform/video.py
next_gen_ui_agent/data_transform/validation/__init__.py
next_gen_ui_agent/data_transform/validation/assertions.py
next_gen_ui_agent/data_transform/validation/types.py
next_gen_ui_agent/input_data_transform/__init__.py
next_gen_ui_agent/input_data_transform/csv_input_data_transformer.py
next_gen_ui_agent/input_data_transform/fwctable_input_data_transformer.py
next_gen_ui_agent/input_data_transform/input_data_transform.py
next_gen_ui_agent/input_data_transform/json_input_data_transformer.py
next_gen_ui_agent/input_data_transform/noop_input_data_transformer.py
next_gen_ui_agent/input_data_transform/yaml_input_data_transformer.py
next_gen_ui_agent/renderer/__init__.py
next_gen_ui_agent/renderer/audio.py
next_gen_ui_agent/renderer/base_renderer.py
next_gen_ui_agent/renderer/hand_build_component.py
next_gen_ui_agent-0.3.0.dist-info/METADATA
next_gen_ui_agent-0.3.0.dist-info/WHEEL
next_gen_ui_agent-0.3.0.dist-info/namespace_packages.txt
next_gen_ui_agent-0.3.0.dist-info/top_level.txt
next_gen_ui_agent-0.3.0.dist-info/RECORD
