Metadata-Version: 2.1
Name: next_gen_ui_agent
Version: 0.3.0
Summary: Empower your UI by AI Agent
Home-page: https://github.com/RedHat-UX/next-gen-ui-agent
License: Apache-2.0
Classifier: Programming Language :: Python :: 3
Classifier: Programming Language :: Python :: 3.12
Classifier: Programming Language :: Python :: 3.13
Classifier: License :: OSI Approved :: Apache Software License
Requires-Python: <3.14,>=3.12
Requires-Dist: jsonpath-ng
Requires-Dist: pydantic
Requires-Dist: pydantic-core
Requires-Dist: pyyaml>=5.3.1
Requires-Dist: stevedore==5.4.1
Requires-Dist: typing-extensions
